pymihome/__init__.py
pymihome/pymihome.py
pymihome-0.0.5.dist-info/DESCRIPTION.rst
pymihome-0.0.5.dist-info/METADATA
pymihome-0.0.5.dist-info/RECORD
pymihome-0.0.5.dist-info/WHEEL
pymihome-0.0.5.dist-info/metadata.json
pymihome-0.0.5.dist-info/top_level.txt
