Metadata-Version: 2.0
Name: pymihome
Version: 0.0.5
Summary: Library to access Energenie MiHome devices via the web API.
Home-page: https://github.com/ng110/pymihome
Author: Neil Griffin
Author-email: ngriffin110@gmail.com
License: LGPLv3
Download-URL: https://github.com/ng110/pymihome/tarball/0.0.5
Requires-Dist: requests
